MANIFEST.in
setup.cfg
setup.py
versioneer.py
mypackage/__init__.py
mypackage/_version.py
mypackage/api/__init__.py
mypackage/api/common.py
mypackage/api/test.py
mypackage/campaigns/__init__.py
mypackage/config/__init__.py
mypackage/contacthub/__init__.py
mypackage/contacthub/common.py
mypackage/dataload/__init__.py
mypackage/dataload/common.py
mypackage/gcp/__init__.py
mypackage/gcp/common.py
mypackage/gcp/common_bk.py
mypackage/gcp/process.py
mypackage/utils/__init__.py
mypackage/utils/common.py
pypipackage.egg-info/PKG-INFO
pypipackage.egg-info/SOURCES.txt
pypipackage.egg-info/dependency_links.txt
pypipackage.egg-info/top_level.txt