Metadata-Version: 1.0
Name: pypipackage
Version: 1.5.0
Summary: The shared resources project
Home-page: https://github.com/vasu4132/pypi-package.git
Author: vasu
Author-email: vasuchowdary413@gmail.com
License: UNKNOWN
Platform: UNKNOWN
